<?xml version="1.0" encoding="ISO-8859-1"?>
<!DOCTYPE polygonSet SYSTEM "../../dtd/polygonSet.dtd">
<polygonSet>
    <name>fractured_berg</name>
    <shapeType>CUBIC_CURVE</shapeType>
    <polygon>
        <curve>
            <point x="-0.41000000000000003" y="0.020000000000000018"/>
            <point x="-0.4" y="-0.04666666666666669"/>
            <point x="-0.39" y="-0.1133333333333334"/>
            <point x="-0.38" y="-0.18"/>
        </curve>
        <curve>
            <point x="-0.38" y="-0.18"/>
            <point x="-0.3466666666666667" y="-0.18"/>
            <point x="-0.31333333333333335" y="-0.18"/>
            <point x="-0.28" y="-0.18"/>
        </curve>
        <curve>
            <point x="-0.28" y="-0.18"/>
            <point x="-0.2733333333333333" y="-0.11333333333333334"/>
            <point x="-0.26666666666666666" y="-0.046666666666666634"/>
            <point x="-0.26" y="0.020000000000000018"/>
        </curve>
        <curve>
            <point x="-0.26" y="0.020000000000000018"/>
            <point x="-0.31" y="0.020000000000000018"/>
            <point x="-0.36" y="0.020000000000000018"/>
            <point x="-0.41000000000000003" y="0.020000000000000018"/>
        </curve>
    </polygon>
    <polygon>
        <curve>
            <point x="-0.29000000000000004" y="0.020000000000000018"/>
            <point x="-0.28" y="-0.04666666666666669"/>
            <point x="-0.27" y="-0.1133333333333334"/>
            <point x="-0.26" y="-0.18"/>
        </curve>
        <curve>
            <point x="-0.26" y="-0.18"/>
            <point x="-0.22666666666666668" y="-0.18"/>
            <point x="-0.1933333333333333" y="-0.18"/>
            <point x="-0.15999999999999998" y="-0.18"/>
        </curve>
        <curve>
            <point x="-0.15999999999999998" y="-0.18"/>
            <point x="-0.15333333333333332" y="-0.11333333333333334"/>
            <point x="-0.14666666666666667" y="-0.046666666666666634"/>
            <point x="-0.14" y="0.020000000000000018"/>
        </curve>
        <curve>
            <point x="-0.14" y="0.020000000000000018"/>
            <point x="-0.19" y="0.020000000000000018"/>
            <point x="-0.24" y="0.020000000000000018"/>
            <point x="-0.29000000000000004" y="0.020000000000000018"/>
        </curve>
    </polygon>
    <polygon>
        <curve>
            <point x="-0.18" y="0.020000000000000018"/>
            <point x="-0.16999999999999998" y="-0.04666666666666669"/>
            <point x="-0.15999999999999998" y="-0.1133333333333334"/>
            <point x="-0.15000000000000002" y="-0.18"/>
        </curve>
        <curve>
            <point x="-0.15000000000000002" y="-0.18"/>
            <point x="-0.12" y="-0.18"/>
            <point x="-0.09000000000000002" y="-0.18"/>
            <point x="-0.06" y="-0.18"/>
        </curve>
        <curve>
            <point x="-0.06" y="-0.18"/>
            <point x="-0.04999999999999999" y="-0.11333333333333334"/>
            <point x="-0.03999999999999998" y="-0.046666666666666634"/>
            <point x="-0.030000000000000027" y="0.020000000000000018"/>
        </curve>
        <curve>
            <point x="-0.030000000000000027" y="0.020000000000000018"/>
            <point x="-0.08000000000000002" y="0.020000000000000018"/>
            <point x="-0.13" y="0.020000000000000018"/>
            <point x="-0.18" y="0.020000000000000018"/>
        </curve>
    </polygon>
    <polygon>
        <curve>
            <point x="-0.07" y="0.020000000000000018"/>
            <point x="-0.07" y="-0.04666666666666669"/>
            <point x="-0.07" y="-0.1133333333333334"/>
            <point x="-0.07" y="-0.18"/>
        </curve>
        <curve>
            <point x="-0.07" y="-0.18"/>
            <point x="-0.033333333333333326" y="-0.18"/>
            <point x="0.0033333333333332993" y="-0.18"/>
            <point x="0.040000000000000036" y="-0.18"/>
        </curve>
        <curve>
            <point x="0.040000000000000036" y="-0.18"/>
            <point x="0.043333333333333335" y="-0.11333333333333334"/>
            <point x="0.046666666666666634" y="-0.046666666666666634"/>
            <point x="0.050000000000000044" y="0.020000000000000018"/>
        </curve>
        <curve>
            <point x="0.050000000000000044" y="0.020000000000000018"/>
            <point x="0.010000000000000009" y="0.020000000000000018"/>
            <point x="-0.030000000000000027" y="0.020000000000000018"/>
            <point x="-0.07" y="0.020000000000000018"/>
        </curve>
    </polygon>
    <polygon>
        <curve>
            <point x="0.030000000000000027" y="0.020000000000000018"/>
            <point x="0.036666666666666625" y="-0.04666666666666669"/>
            <point x="0.043333333333333335" y="-0.1133333333333334"/>
            <point x="0.050000000000000044" y="-0.18"/>
        </curve>
        <curve>
            <point x="0.050000000000000044" y="-0.18"/>
            <point x="0.08333333333333337" y="-0.18"/>
            <point x="0.11666666666666659" y="-0.18"/>
            <point x="0.15000000000000002" y="-0.18"/>
        </curve>
        <curve>
            <point x="0.15000000000000002" y="-0.18"/>
            <point x="0.15666666666666662" y="-0.11333333333333334"/>
            <point x="0.16333333333333333" y="-0.046666666666666634"/>
            <point x="0.17000000000000004" y="0.020000000000000018"/>
        </curve>
        <curve>
            <point x="0.17000000000000004" y="0.020000000000000018"/>
            <point x="0.1233333333333334" y="0.020000000000000018"/>
            <point x="0.07666666666666666" y="0.020000000000000018"/>
            <point x="0.030000000000000027" y="0.020000000000000018"/>
        </curve>
    </polygon>
    <polygon>
        <curve>
            <point x="0.14" y="0.020000000000000018"/>
            <point x="0.1466666666666666" y="-0.04666666666666669"/>
            <point x="0.15333333333333332" y="-0.1133333333333334"/>
            <point x="0.16000000000000003" y="-0.18"/>
        </curve>
        <curve>
            <point x="0.16000000000000003" y="-0.18"/>
            <point x="0.19666666666666666" y="-0.18"/>
            <point x="0.2333333333333334" y="-0.18"/>
            <point x="0.27" y="-0.18"/>
        </curve>
        <curve>
            <point x="0.27" y="-0.18"/>
            <point x="0.2733333333333333" y="-0.11333333333333334"/>
            <point x="0.2766666666666666" y="-0.046666666666666634"/>
            <point x="0.28" y="0.020000000000000018"/>
        </curve>
        <curve>
            <point x="0.28" y="0.020000000000000018"/>
            <point x="0.2333333333333334" y="0.020000000000000018"/>
            <point x="0.18666666666666665" y="0.020000000000000018"/>
            <point x="0.14" y="0.020000000000000018"/>
        </curve>
    </polygon>
    <polygon>
        <curve>
            <point x="0.25" y="0.020000000000000018"/>
            <point x="0.2633333333333334" y="-0.04666666666666669"/>
            <point x="0.2766666666666666" y="-0.1133333333333334"/>
            <point x="0.29000000000000004" y="-0.18"/>
        </curve>
        <curve>
            <point x="0.29000000000000004" y="-0.18"/>
            <point x="0.32666666666666666" y="-0.18"/>
            <point x="0.3633333333333334" y="-0.18"/>
            <point x="0.4" y="-0.18"/>
        </curve>
        <curve>
            <point x="0.4" y="-0.18"/>
            <point x="0.41666666666666663" y="-0.11333333333333334"/>
            <point x="0.43333333333333335" y="-0.046666666666666634"/>
            <point x="0.44999999999999996" y="0.020000000000000018"/>
        </curve>
        <curve>
            <point x="0.44999999999999996" y="0.020000000000000018"/>
            <point x="0.3833333333333334" y="0.020000000000000018"/>
            <point x="0.31666666666666665" y="0.020000000000000018"/>
            <point x="0.25" y="0.020000000000000018"/>
        </curve>
    </polygon>
    <scaleX>1.0</scaleX>
    <scaleY>1.0</scaleY>
    <rotationAngle>0.0</rotationAngle>
    <transX>0.5</transX>
    <transY>0.5</transY>
</polygonSet>
